{
  "db_name": "PostgreSQL",
  "query": "select\n  id,\n  title,\n  base_url\nfrom iiif_source\nwhere id = any($1)\n",
  "describe": {
    "columns": [
      {
        "ordinal": 0,
        "name": "id",
        "type_info": "Uuid"
      },
      {
        "ordinal": 1,
        "name": "title",
        "type_info": "Text"
      },
      {
        "ordinal": 2,
        "name": "base_url",
        "type_info": "Text"
      }
    ],
    "parameters": {
      "Left": [
        "UuidArray"
      ]
    },
    "nullable": [
      false,
      false,
      false
    ]
  },
  "hash": "d8bc89c2d802ac2da071308eb27bdd1bc2bbdc31d64e8ccad71d4b861f8be12b"
}
